{
  "profile": {
    "name": "Ravi Teja Arcot",
    "title": "Analytics Engineer",
    "bio": "Analytics Engineer and Data Engineer with 4+ years of experience building modern data platforms, analytics solutions, and cloud-based data pipelines using dbt, Snowflake, Python, SQL, Airflow, Databricks, Spark, Kafka, AWS, and Azure. I design scalable ETL/ELT pipelines, dimensional data models, and analytics-ready datasets that power executive reporting, financial analytics, self-service BI, and machine learning initiatives. My focus is data warehousing, cloud analytics, data governance, and data quality across the modern data stack, delivering trusted data solutions that both technical and business stakeholders rely on."
  },
  "contact": {
    "email": "arcotravi90@gmail.com",
    "phone": "+1 (414)-460-4612",
    "githubUsername": "arcotraviteja",
    "linkedin": "https://www.linkedin.com/in/ravi-a-300b553b4/?isSelfProfile=false"
  },
  "siteConfig": {
    "domain": "raviteja.tech",
    "title": "Ravi Teja Arcot - Portfolio",
    "description": "Analytics Engineer and Data Engineer with 4+ years building modern data platforms, scalable ETL/ELT pipelines, dimensional data models, and analytics-ready datasets using dbt, Snowflake, Python, SQL, Airflow, Spark, Kafka, AWS, and Azure."
  }
}
